mkpy224o/__init__.py
mkpy224o/version.py
mkpy224o-0.1.5.dist-info/LICENSE
mkpy224o-0.1.5.dist-info/METADATA
mkpy224o-0.1.5.dist-info/WHEEL
mkpy224o-0.1.5.dist-info/top_level.txt
mkpy224o-0.1.5.dist-info/RECORD
