Metadata-Version: 2.1
Name: mkpy224o
Version: 0.1.5
Summary: A python library to control wpa_supplicant via it's control socket.
Home-page: http://github.com/btimby/mkpy224o/
Author: Ben Timby
Author-email: btimby@gmail.com
Maintainer: Ben Timby
Maintainer-email: btimby@gmail.com
License: MIT
Platform: UNKNOWN
Classifier: Development Status :: 4 - Beta
Classifier: Intended Audience :: Developers
Classifier: Operating System :: OS Independent
Classifier: Programming Language :: Python :: 2
Classifier: Programming Language :: Python :: 3
Classifier: Topic :: Software Development :: Libraries :: Python Modules
License-File: LICENSE
